LICENSE
MANIFEST.in
Makefile
README.md
requirements.txt
setup.py
pmk.egg-info/PKG-INFO
pmk.egg-info/SOURCES.txt
pmk.egg-info/dependency_links.txt
pmk.egg-info/entry_points.txt
pmk.egg-info/requires.txt
pmk.egg-info/top_level.txt
pymake/__init__.py
pymake/_version.py
pymake/exceptions.py
pymake/io.py
pymake/manager.py
pymake/model.py
pymake/plot.py
pymake/zymake.py
pymake/core/__init__.py
pymake/core/format.py
pymake/core/gram.py
pymake/core/gramexp.py
pymake/core/logformatter.py
pymake/core/types.py
pymake/frontend/__init__.py
pymake/frontend/drivers.py
pymake/frontend/frontend.py
pymake/frontend/frontendnetwork.py
pymake/frontend/frontendnetwork_gt.py
pymake/frontend/frontendtext.py
pymake/frontend/io.py
pymake/frontend/manager.py
pymake/index/__init__.py
pymake/index/indexmanager.py
pymake/template/gitignore.template
pymake/template/gramarg.template
pymake/template/model.template
pymake/template/pmk.cfg.template
pymake/template/pymake_completion.template
pymake/template/script.template
pymake/template/spec.template
pymake/util/__init__.py
pymake/util/algo.py
pymake/util/ascii_code.py
pymake/util/colors.py
pymake/util/compute_stirling.py
pymake/util/math.py
pymake/util/scaled_image.py
pymake/util/utils.py
pymake/util/vocabulary.py