Metadata-Version: 2.1
Name: pmk
Version: 0.43.5
Summary: An experiment control system for reproducible research.
Home-page: https://github.com/dtrckd/pymake
Author: dtrckd
Author-email: dtrckd@gmail.com
License: GPL
Keywords: pymake,learning,model
Classifier: Topic :: Scientific/Engineering
Classifier: Topic :: Scientific/Engineering :: Visualization
Classifier: Topic :: Scientific/Engineering :: Information Analysis
Classifier: Topic :: Scientific/Engineering :: Artificial Intelligence
Classifier: Topic :: Scientific/Engineering :: Human Machine Interfaces
Classifier: Topic :: Software Development :: Libraries :: Application Frameworks
Classifier: Intended Audience :: Developers
Classifier: Intended Audience :: Education
Classifier: Intended Audience :: Information Technology
Classifier: Intended Audience :: Science/Research
Classifier: Programming Language :: Python :: 3
License-File: LICENSE
